{
    "swagger": "2.0",
    "info": {
        "description": "API service to manage user balance, payments and get revenue reports",
        "title": "Balance Service API",
        "contact": {},
        "version": "1.0"
    },
    "host": "localhost:8071",
    "paths": {
        "/api/add": {
            "post": {
                "consumes": [
                    "application/json"
                ],
                "produces": [
                    "application/json"
                ],
                "tags": [
                    "user balance"
                ],
                "summary": "Add amount to user account",
                "parameters": [
                    {
                        "description": "user id and amount",
                        "name": "input",
                        "in": "body",
                        "required": true,
                        "schema": {
                            "$ref": "#/definitions/entities.AddRequest"
                        }
                    }
                ],
                "responses": {
                    "200": {
                        "description": "OK",
                        "schema": {
                            "$ref": "#/definitions/entities.ResultResponse"
                        }
                    },
                    "400": {
                        "description": "Bad Request",
                        "schema": {
                            "$ref": "#/definitions/entities.ErrorResponse"
                        }
                    },
                    "404": {
                        "description": "Not Found",
                        "schema": {
                            "$ref": "#/definitions/entities.ErrorResponse"
                        }
                    }
                }
            }
        },
        "/api/approve": {
            "post": {
                "consumes": [
                    "application/json"
                ],
                "produces": [
                    "application/json"
                ],
                "tags": [
                    "user balance"
                ],
                "summary": "Approve payment transaction",
                "parameters": [
                    {
                        "description": "user id,order_id, service_id to reserve funds for approve payment service",
                        "name": "input",
                        "in": "body",
                        "required": true,
                        "schema": {
                            "$ref": "#/definitions/entities.Request"
                        }
                    }
                ],
                "responses": {
                    "200": {
                        "description": "OK",
                        "schema": {
                            "$ref": "#/definitions/entities.ResultResponse"
                        }
                    },
                    "400": {
                        "description": "Bad Request",
                        "schema": {
                            "$ref": "#/definitions/entities.ErrorResponse"
                        }
                    },
                    "404": {
                        "description": "Not Found",
                        "schema": {
                            "$ref": "#/definitions/entities.ErrorResponse"
                        }
                    }
                }
            }
        },
        "/api/get": {
            "get": {
                "consumes": [
                    "application/json"
                ],
                "produces": [
                    "application/json"
                ],
                "tags": [
                    "user balance"
                ],
                "summary": "balance user balance",
                "parameters": [
                    {
                        "description": "user id for its balance",
                        "name": "input",
                        "in": "body",
                        "required": true,
                        "schema": {
                            "$ref": "#/definitions/entities.UserBalanceRequest"
                        }
                    }
                ],
                "responses": {
                    "200": {
                        "description": "OK",
                        "schema": {
                            "$ref": "#/definitions/entities.ResultResponse"
                        }
                    },
                    "400": {
                        "description": "Bad Request",
                        "schema": {
                            "$ref": "#/definitions/entities.ErrorResponse"
                        }
                    },
                    "404": {
                        "description": "Not Found",
                        "schema": {
                            "$ref": "#/definitions/entities.ErrorResponse"
                        }
                    }
                }
            }
        },
        "/api/reject": {
            "post": {
                "consumes": [
                    "application/json"
                ],
                "produces": [
                    "application/json"
                ],
                "tags": [
                    "user balance"
                ],
                "summary": "Reject reserving and refund money",
                "parameters": [
                    {
                        "description": "user id and order id for reject the reservation",
                        "name": "input",
                        "in": "body",
                        "required": true,
                        "schema": {
                            "$ref": "#/definitions/entities.ReserveReject"
                        }
                    }
                ],
                "responses": {
                    "200": {
                        "description": "OK",
                        "schema": {
                            "$ref": "#/definitions/entities.ResultResponse"
                        }
                    },
                    "400": {
                        "description": "Bad Request",
                        "schema": {
                            "$ref": "#/definitions/entities.ErrorResponse"
                        }
                    },
                    "404": {
                        "description": "Not Found",
                        "schema": {
                            "$ref": "#/definitions/entities.ErrorResponse"
                        }
                    }
                }
            }
        },
        "/api/report": {
            "get": {
                "consumes": [
                    "application/json"
                ],
                "produces": [
                    "application/json"
                ],
                "tags": [
                    "report"
                ],
                "summary": "Create and get path to csv file with report",
                "parameters": [
                    {
                        "description": "Month for report. Format: 2022-11",
                        "name": "input",
                        "in": "body",
                        "required": true,
                        "schema": {
                            "$ref": "#/definitions/entities.ReportRequest"
                        }
                    }
                ],
                "responses": {
                    "200": {
                        "description": "OK",
                        "schema": {
                            "$ref": "#/definitions/entities.ResultResponse"
                        }
                    },
                    "400": {
                        "description": "Bad Request",
                        "schema": {
                            "$ref": "#/definitions/entities.ErrorResponse"
                        }
                    },
                    "404": {
                        "description": "Not Found",
                        "schema": {
                            "$ref": "#/definitions/entities.ErrorResponse"
                        }
                    }
                }
            }
        },
        "/api/reserve": {
            "post": {
                "consumes": [
                    "application/json"
                ],
                "produces": [
                    "application/json"
                ],
                "tags": [
                    "user balance"
                ],
                "summary": "Reserve funds on user account",
                "parameters": [
                    {
                        "description": "user id,order_id, service_id to reserve funds for service",
                        "name": "input",
                        "in": "body",
                        "required": true,
                        "schema": {
                            "$ref": "#/definitions/entities.Request"
                        }
                    }
                ],
                "responses": {
                    "200": {
                        "description": "OK",
                        "schema": {
                            "$ref": "#/definitions/entities.ResultResponse"
                        }
                    },
                    "400": {
                        "description": "Bad Request",
                        "schema": {
                            "$ref": "#/definitions/entities.ErrorResponse"
                        }
                    },
                    "404": {
                        "description": "Not Found",
                        "schema": {
                            "$ref": "#/definitions/entities.ErrorResponse"
                        }
                    }
                }
            }
        },
        "/api/transfer": {
            "post": {
                "consumes": [
                    "application/json"
                ],
                "produces": [
                    "application/json"
                ],
                "tags": [
                    "user balance"
                ],
                "summary": "Create transfer between users",
                "parameters": [
                    {
                        "description": "src user id,dest user id, amount to transfer money",
                        "name": "input",
                        "in": "body",
                        "required": true,
                        "schema": {
                            "$ref": "#/definitions/entities.TransferRequest"
                        }
                    }
                ],
                "responses": {
                    "200": {
                        "description": "OK",
                        "schema": {
                            "$ref": "#/definitions/entities.ResultResponse"
                        }
                    },
                    "400": {
                        "description": "Bad Request",
                        "schema": {
                            "$ref": "#/definitions/entities.ErrorResponse"
                        }
                    },
                    "404": {
                        "description": "Not Found",
                        "schema": {
                            "$ref": "#/definitions/entities.ErrorResponse"
                        }
                    }
                }
            }
        },
        "/api/userReport": {
            "get": {
                "consumes": [
                    "application/json"
                ],
                "produces": [
                    "application/json"
                ],
                "tags": [
                    "report"
                ],
                "summary": "Get user transactions/transfers/reserver report",
                "parameters": [
                    {
                        "description": "User id for report",
                        "name": "input",
                        "in": "body",
                        "required": true,
                        "schema": {
                            "$ref": "#/definitions/entities.ReportRequest"
                        }
                    }
                ],
                "responses": {
                    "200": {
                        "description": "OK",
                        "schema": {
                            "$ref": "#/definitions/entities.ResultResponse"
                        }
                    },
                    "400": {
                        "description": "Bad Request",
                        "schema": {
                            "$ref": "#/definitions/entities.ErrorResponse"
                        }
                    },
                    "404": {
                        "description": "Not Found",
                        "schema": {
                            "$ref": "#/definitions/entities.ErrorResponse"
                        }
                    }
                }
            }
        }
    },
    "definitions": {
        "entities.AddRequest": {
            "type": "object",
            "properties": {
                "amount": {
                    "type": "number"
                },
                "id": {
                    "type": "integer"
                }
            }
        },
        "entities.ErrorResponse": {
            "type": "object",
            "properties": {
                "error": {
                    "type": "string"
                }
            }
        },
        "entities.ReportRequest": {
            "type": "object",
            "properties": {
                "date": {
                    "type": "string"
                }
            }
        },
        "entities.Request": {
            "type": "object",
            "properties": {
                "amount": {
                    "type": "number"
                },
                "id": {
                    "type": "integer"
                },
                "order_id": {
                    "type": "integer"
                },
                "service_id": {
                    "type": "integer"
                }
            }
        },
        "entities.ReserveReject": {
            "type": "object",
            "properties": {
                "id": {
                    "type": "integer"
                },
                "order_id": {
                    "type": "integer"
                }
            }
        },
        "entities.ResultResponse": {
            "type": "object",
            "properties": {
                "result": {}
            }
        },
        "entities.TransferRequest": {
            "type": "object",
            "properties": {
                "amount": {
                    "type": "number"
                },
                "dest_id": {
                    "type": "integer"
                },
                "src_id": {
                    "type": "integer"
                }
            }
        },
        "entities.UserBalanceRequest": {
            "type": "object",
            "properties": {
                "id": {
                    "type": "integer"
                }
            }
        }
    }
}